SBSGdb/__init__.py
SBSGdb/buffers_functions.py
SBSGdb/energy_solution_functions.py
SBSGdb/login.py
SBSGdb/lysate_systems_functions.py
SBSGdb/template_sequences_functions.py
SBSGdbee-0.0.1.dist-info/METADATA
SBSGdbee-0.0.1.dist-info/WHEEL
SBSGdbee-0.0.1.dist-info/top_level.txt
SBSGdbee-0.0.1.dist-info/RECORD
